pyexperian/__init__.py
pyexperian/constants.py
pyexperian/exceptions.py
pyexperian/services.py
pyexperian/session.py
pyexperian/lib/__init__.py
pyexperian/lib/dicttoxml.py
pyexperian/test/__init__.py
pyexperian/test/ecals_tests.py
pyexperian-1.0.2.dist-info/DESCRIPTION.rst
pyexperian-1.0.2.dist-info/METADATA
pyexperian-1.0.2.dist-info/RECORD
pyexperian-1.0.2.dist-info/WHEEL
pyexperian-1.0.2.dist-info/metadata.json
pyexperian-1.0.2.dist-info/top_level.txt
