Metadata-Version: 2.0
Name: pyexperian
Version: 1.0.2
Summary: Python wrapper for Experian's Net Connect API
Home-page: https://github.com/AbleEng/pyexperian
Author: Carlos e. Rivera
Author-email: carlos@ablelending.com
License: UNKNOWN
Download-URL: https://github.com/AbleEng/pyexperian
Keywords: experian netconnect ecals
Platform: UNKNOWN
Requires-Dist: requests (>=2.2.1)
Requires-Dist: xmltodict (>=0.9.0)
